legcop/__init__.py
legiscan/__init__.py
legcop-0.0.5.dist-info/LICENSE
legcop-0.0.5.dist-info/METADATA
legcop-0.0.5.dist-info/WHEEL
legcop-0.0.5.dist-info/top_level.txt
legcop-0.0.5.dist-info/RECORD
