Metadata-Version: 2.1
Name: legcop
Version: 0.0.5
Summary: API utilities to access legislative information from across the 54 U.S. States and Territories
Home-page: https://github.com/jamestollefson/legcop
Author: James Tollefson
Author-email: james.l.tollefson@alaskaupdate.com
License: UNKNOWN
Platform: UNKNOWN
Classifier: Programming Language :: Python :: 3
Classifier: License :: OSI Approved :: MIT License
Classifier: Operating System :: OS Independent
Requires-Python: >=3.6
